{
  "generator-jhipster": {
    "jhipsterVersion": "3.12.2",
    "baseName": "catalog",
    "packageName": "com.microservice",
    "packageFolder": "com/microservice",
    "serverPort": "8081",
    "authenticationType": "jwt",
    "hibernateCache": "no",
    "clusteredHttpSession": false,
    "websocket": false,
    "databaseType": "mongodb",
    "devDatabaseType": "mongodb",
    "prodDatabaseType": "mongodb",
    "searchEngine": false,
    "messageBroker": false,
    "serviceDiscoveryType": false,
    "buildTool": "maven",
    "enableSocialSignIn": false,
    "jwtSecretKey": "5c747962ca39c9b40f99616d95da99f13a767c7b",
    "enableTranslation": false,
    "applicationType": "microservice",
    "testFrameworks": [
      "gatling"
    ],
    "jhiPrefix": "jhi",
    "skipClient": true,
    "skipUserManagement": true
  }
}